{
  "dev": {
    "awscloudformation": {
      "AuthRoleName": "amplify-moviesearch-dev-130138-authRole",
      "UnauthRoleArn": "arn:aws:iam::783132387106:role/amplify-moviesearch-dev-130138-unauthRole",
      "AuthRoleArn": "arn:aws:iam::783132387106:role/amplify-moviesearch-dev-130138-authRole",
      "Region": "us-east-2",
      "DeploymentBucketName": "amplify-moviesearch-dev-130138-deployment",
      "UnauthRoleName": "amplify-moviesearch-dev-130138-unauthRole",
      "StackName": "amplify-moviesearch-dev-130138",
      "StackId": "arn:aws:cloudformation:us-east-2:783132387106:stack/amplify-moviesearch-dev-130138/8559a3d0-af21-11ee-b958-0ab5d038b31d",
      "AmplifyAppId": "d3ocxza0j6v5ik"
    },
    "categories": {
      "custom": {
        "codecommit": {},
        "opensearchserverless": {},
        "waf01222014": {}
      },
      "function": {
        "moviesearch56199296": {
          "deploymentBucketName": "amplify-moviesearch-dev-130138-deployment",
          "s3Key": "amplify-builds/moviesearch56199296-384647456b2f796b4156-build.zip",
          "region": "us-east-2"
        }
      },
      "auth": {
        "moviesearchbf5c44f3": {}
      },
      "api": {
        "moviesearchapi": {}
      },
      "storage": {
        "moviestore": {}
      },
      "hosting": {
        "amplifyhosting": {
          "appId": "d3ocxza0j6v5ik",
          "type": "cicd"
        }
      }
    }
  }
}